ProtPeptigram/DataProcessor.py
ProtPeptigram/__init__.py
ProtPeptigram/logger.py
ProtPeptigram/main.py
ProtPeptigram/runner.py
ProtPeptigram/viz.py
protpeptigram-1.0.0.dist-info/METADATA
protpeptigram-1.0.0.dist-info/WHEEL
protpeptigram-1.0.0.dist-info/entry_points.txt
protpeptigram-1.0.0.dist-info/top_level.txt
protpeptigram-1.0.0.dist-info/RECORD
