Metadata-Version: 2.4
Name: ProtPeptigram
Version: 1.0.0
Summary: Mapping peptides to source protein for immunopeptidiomics data analysis
Home-page: https://github.com/Sanpme66/ProtPeptigram
Author: Sanjay Krishna
Author-email: sanjay.sondekoppagopalakrishna@monash.edu
Project-URL: Documentation, https://github.com/Sanpme66/ProtPeptigram
Project-URL: Bug Reports, https://github.com/Sanpme66/ProtPeptigram/issues
Project-URL: Source Code, https://github.com/Sanpme66/ProtPeptigram
Keywords: proteomics,peptides,visualization,bioinformatics,immunopeptidome
Classifier: Development Status :: 4 - Beta
Classifier: Intended Audience :: Science/Research
Classifier: Topic :: Scientific/Engineering :: Bio-Informatics
Classifier: Programming Language :: Python :: 3
Classifier: Programming Language :: Python :: 3.8
Classifier: Programming Language :: Python :: 3.9
Classifier: Programming Language :: Python :: 3.10
Classifier: License :: OSI Approved :: MIT License
Classifier: Operating System :: OS Independent
Requires-Python: >=3.10
Requires-Dist: pandas>=1.3.0
Requires-Dist: numpy>=1.20.0
Requires-Dist: matplotlib>=3.4.0
Requires-Dist: seaborn>=0.11.0
Requires-Dist: biopython>=1.79
Requires-Dist: rich>=10.0.0
Requires-Dist: rich-argparse>=0.5.0
Requires-Dist: click>=8.0.0
Dynamic: author
Dynamic: author-email
Dynamic: classifier
Dynamic: description
Dynamic: description-content-type
Dynamic: home-page
Dynamic: keywords
Dynamic: project-url
Dynamic: requires-dist
Dynamic: requires-python
Dynamic: summary
